capeditor/__init__.py
capeditor/admin.py
capeditor/apps.py
capeditor/blocks.py
capeditor/cap_settings.py
capeditor/caputils.py
capeditor/clear_fuzzy.py
capeditor/constants.py
capeditor/errors.py
capeditor/models.py
capeditor/renderers.py
capeditor/serializers.py
capeditor/tests.py
capeditor/utils.py
capeditor/views.py
capeditor/wagtail_hooks.py
capeditor/forms/__init__.py
capeditor/forms/capimporter.py
capeditor/forms/fields.py
capeditor/forms/widgets.py
capeditor/locale/am/LC_MESSAGES/django.mo
capeditor/locale/am/LC_MESSAGES/django.po
capeditor/locale/ar/LC_MESSAGES/django.mo
capeditor/locale/ar/LC_MESSAGES/django.po
capeditor/locale/en/LC_MESSAGES/django.mo
capeditor/locale/en/LC_MESSAGES/django.po
capeditor/locale/es/LC_MESSAGES/django.mo
capeditor/locale/es/LC_MESSAGES/django.po
capeditor/locale/fr/LC_MESSAGES/django.mo
capeditor/locale/fr/LC_MESSAGES/django.po
capeditor/locale/sw/LC_MESSAGES/django.mo
capeditor/locale/sw/LC_MESSAGES/django.po
capeditor/migrations/0001_initial.py
capeditor/migrations/0002_alter_capsetting_options_and_more.py
capeditor/migrations/0003_capsetting_logo.py
capeditor/migrations/0004_predefinedalertarea.py
capeditor/migrations/0005_alter_capsetting_sender.py
capeditor/migrations/0006_capsetting_wmo_oid.py
capeditor/migrations/0007_alter_capsetting_wmo_oid_and_more.py
capeditor/migrations/0008_remove_capsetting_audience_types.py
capeditor/migrations/0009_capsetting_un_country_boundary_geojson.py
capeditor/migrations/0010_alter_capsetting_un_country_boundary_geojson.py
capeditor/migrations/0011_alertlanguage.py
capeditor/migrations/__init__.py
capeditor/pubsub/__init__.py
capeditor/pubsub/base.py
capeditor/pubsub/mqtt.py
capeditor/pubsub/publish.py
capeditor/static/capeditor/css/cap_detail_page.css
capeditor/static/capeditor/css/import_cap_preview.css
capeditor/static/capeditor/css/mapbox-gl-draw.css
capeditor/static/capeditor/css/maplibre-gl.css
capeditor/static/capeditor/css/widget/boundary-widget.css
capeditor-0.6.6.dist-info/METADATA
capeditor-0.6.6.dist-info/WHEEL
capeditor-0.6.6.dist-info/top_level.txt
capeditor-0.6.6.dist-info/RECORD
